decomon/__init__.py
decomon/core.py
decomon/keras_utils.py
decomon/utils.py
decomon/wrapper.py
decomon/wrapper_with_tuning.py
decomon/backward_layers/__init__.py
decomon/backward_layers/activations.py
decomon/backward_layers/backward_layers.py
decomon/backward_layers/backward_maxpooling.py
decomon/backward_layers/backward_merge.py
decomon/backward_layers/backward_reshape.py
decomon/backward_layers/convert.py
decomon/backward_layers/core.py
decomon/backward_layers/utils.py
decomon/backward_layers/utils_conv.py
decomon/layers/__init__.py
decomon/layers/activations.py
decomon/layers/convert.py
decomon/layers/core.py
decomon/layers/decomon_layers.py
decomon/layers/decomon_merge_layers.py
decomon/layers/decomon_reshape.py
decomon/layers/maxpooling.py
decomon/layers/utils.py
decomon/layers/utils_pooling.py
decomon/metrics/__init__.py
decomon/metrics/complexity.py
decomon/metrics/loss.py
decomon/metrics/metric.py
decomon/metrics/utils.py
decomon/models/__init__.py
decomon/models/backward_cloning.py
decomon/models/convert.py
decomon/models/crown.py
decomon/models/forward_cloning.py
decomon/models/models.py
decomon/models/utils.py
decomon/types/__init__.py
decomon-0.2.1.dist-info/LICENSE
decomon-0.2.1.dist-info/METADATA
decomon-0.2.1.dist-info/WHEEL
decomon-0.2.1.dist-info/top_level.txt
decomon-0.2.1.dist-info/RECORD
