Metadata-Version: 2.1
Name: decomon
Version: 0.2.1
Summary: Linear Relaxation for Certified Robustness Bound for Tensorflow Neural Networks
Author-email: ai.decomon@gmail.com
Project-URL: documentation, https://airbus.github.io/decomon
Project-URL: repository, https://github.com/airbus/decomon
Requires-Python: >=3.9
License-File: LICENSE
Requires-Dist: matplotlib
Requires-Dist: numpy >=1.21
Requires-Dist: keras >=3
Provides-Extra: dev
Requires-Dist: tox >=4.6.4 ; extra == 'dev'
